{
    "materialAssetID": "",
    "impostors": [
        {
            "cellIndex": 3,
            "meshAssetID": "{B8227217-2D12-5D97-9136-B36E936B372D}",
            "worldPosition": {
                "x": 4544.0,
                "y": 4160.0
            }
        },
        {
            "cellIndex": 4,
            "meshAssetID": "{4943C49C-2BAE-543F-AF0B-DA5AEAF9602B}",
            "worldPosition": {
                "x": 4672.0,
                "y": 4160.0
            }
        },
        {
            "cellIndex": 5,
            "meshAssetID": "{B81E6336-1136-5F15-9283-5786EFD95CC8}",
            "worldPosition": {
                "x": 4800.0,
                "y": 4160.0
            }
        },
        {
            "cellIndex": 8,
            "meshAssetID": "{6026F624-CD30-5037-93A9-31575A872ADD}",
            "worldPosition": {
                "x": 5184.0,
                "y": 4160.0
            }
        },
        {
            "cellIndex": 9,
            "meshAssetID": "{19F6CA6D-FA49-51F6-82DE-19B67D986D77}",
            "worldPosition": {
                "x": 5312.0,
                "y": 4160.0
            }
        },
        {
            "cellIndex": 10,
            "meshAssetID": "{9A27B74F-E41E-557C-8355-B337061B6193}",
            "worldPosition": {
                "x": 5440.0,
                "y": 4160.0
            }
        },
        {
            "cellIndex": 11,
            "meshAssetID": "{04FF78DD-F131-5161-A390-4A71CEE19958}",
            "worldPosition": {
                "x": 5568.0,
                "y": 4160.0
            }
        },
        {
            "cellIndex": 19,
            "meshAssetID": "{972394DA-BB8B-5CB9-A186-E71FE738B2CE}",
            "worldPosition": {
                "x": 4544.0,
                "y": 4288.0
            }
        },
        {
            "cellIndex": 20,
            "meshAssetID": "{D82484E2-2B92-57F5-90A2-0A975BB2584C}",
            "worldPosition": {
                "x": 4672.0,
                "y": 4288.0
            }
        },
        {
            "cellIndex": 21,
            "meshAssetID": "{EEE4CA3E-F954-5065-ACDE-A0314974731A}",
            "worldPosition": {
                "x": 4800.0,
                "y": 4288.0
            }
        },
        {
            "cellIndex": 22,
            "meshAssetID": "{37F74E0E-81C0-5005-BABD-CDECEFEFDF3D}",
            "worldPosition": {
                "x": 4928.0,
                "y": 4288.0
            }
        },
        {
            "cellIndex": 23,
            "meshAssetID": "{FFA10C1F-7FD6-58B1-A456-01FE95C1733A}",
            "worldPosition": {
                "x": 5056.0,
                "y": 4288.0
            }
        },
        {
            "cellIndex": 24,
            "meshAssetID": "{EED8706A-0DC2-5B92-9CE2-F9BBA0A6F30B}",
            "worldPosition": {
                "x": 5184.0,
                "y": 4288.0
            }
        },
        {
            "cellIndex": 25,
            "meshAssetID": "{A7B118DF-3660-53EF-BF1A-6CD9B4E82F58}",
            "worldPosition": {
                "x": 5312.0,
                "y": 4288.0
            }
        },
        {
            "cellIndex": 26,
            "meshAssetID": "{E9867C4C-C2B3-517D-8059-FC5C284A5226}",
            "worldPosition": {
                "x": 5440.0,
                "y": 4288.0
            }
        },
        {
            "cellIndex": 27,
            "meshAssetID": "{0B6C86B8-C14D-5FF7-B269-36549AE60D6F}",
            "worldPosition": {
                "x": 5568.0,
                "y": 4288.0
            }
        },
        {
            "cellIndex": 28,
            "meshAssetID": "{20129079-93AB-527D-B8D3-0F9EC76C0947}",
            "worldPosition": {
                "x": 5696.0,
                "y": 4288.0
            }
        },
        {
            "cellIndex": 29,
            "meshAssetID": "{CBCE6434-81D4-59C8-B92A-5BC726AA0C45}",
            "worldPosition": {
                "x": 5824.0,
                "y": 4288.0
            }
        },
        {
            "cellIndex": 30,
            "meshAssetID": "{00F11DAC-3A9C-5445-AC8A-3DC8033D2717}",
            "worldPosition": {
                "x": 5952.0,
                "y": 4288.0
            }
        },
        {
            "cellIndex": 31,
            "meshAssetID": "{B12DC9D2-938B-5E2D-B654-FC4638481BAB}",
            "worldPosition": {
                "x": 6080.0,
                "y": 4288.0
            }
        },
        {
            "cellIndex": 35,
            "meshAssetID": "{B0E4EBD7-C500-5F01-8CB5-BAFDC4E671FD}",
            "worldPosition": {
                "x": 4544.0,
                "y": 4416.0
            }
        },
        {
            "cellIndex": 36,
            "meshAssetID": "{C179C0F1-E671-53AC-AD67-F474FE6C47C4}",
            "worldPosition": {
                "x": 4672.0,
                "y": 4416.0
            }
        },
        {
            "cellIndex": 37,
            "meshAssetID": "{2CFA1AF8-5EC5-523F-AA7A-CBD356AA4E47}",
            "worldPosition": {
                "x": 4800.0,
                "y": 4416.0
            }
        },
        {
            "cellIndex": 38,
            "meshAssetID": "{2DBF61E3-7838-54AC-AFF4-32A62239D8E6}",
            "worldPosition": {
                "x": 4928.0,
                "y": 4416.0
            }
        },
        {
            "cellIndex": 39,
            "meshAssetID": "{96D36B6D-A1D1-5246-8827-C50266F5DA4F}",
            "worldPosition": {
                "x": 5056.0,
                "y": 4416.0
            }
        },
        {
            "cellIndex": 41,
            "meshAssetID": "{82D14CBE-209F-591D-A39E-D40B210F78A4}",
            "worldPosition": {
                "x": 5312.0,
                "y": 4416.0
            }
        },
        {
            "cellIndex": 42,
            "meshAssetID": "{BBEFC9EF-CECE-5F6D-9A82-26F587767978}",
            "worldPosition": {
                "x": 5440.0,
                "y": 4416.0
            }
        },
        {
            "cellIndex": 43,
            "meshAssetID": "{BBC3A957-925D-59E1-8297-4D08F3F8DEE4}",
            "worldPosition": {
                "x": 5568.0,
                "y": 4416.0
            }
        },
        {
            "cellIndex": 44,
            "meshAssetID": "{BDB417FB-36ED-57E0-AA7A-B1201AD52414}",
            "worldPosition": {
                "x": 5696.0,
                "y": 4416.0
            }
        },
        {
            "cellIndex": 45,
            "meshAssetID": "{7214E4C2-CB7A-568B-99A5-24577AB42D3B}",
            "worldPosition": {
                "x": 5824.0,
                "y": 4416.0
            }
        },
        {
            "cellIndex": 46,
            "meshAssetID": "{8085F91E-3B27-565D-A89B-DC352B16807F}",
            "worldPosition": {
                "x": 5952.0,
                "y": 4416.0
            }
        },
        {
            "cellIndex": 47,
            "meshAssetID": "{3C33C30D-8E69-5E26-B1F4-FF3C4E68719F}",
            "worldPosition": {
                "x": 6080.0,
                "y": 4416.0
            }
        },
        {
            "cellIndex": 52,
            "meshAssetID": "{B080FEB9-3BC2-5055-9F04-50E9BFA070EA}",
            "worldPosition": {
                "x": 4672.0,
                "y": 4544.0
            }
        },
        {
            "cellIndex": 53,
            "meshAssetID": "{179887E8-6690-54F1-BA8A-2415A23ABB60}",
            "worldPosition": {
                "x": 4800.0,
                "y": 4544.0
            }
        },
        {
            "cellIndex": 54,
            "meshAssetID": "{5BF02B64-38C4-5EB0-BA60-07D704F159A8}",
            "worldPosition": {
                "x": 4928.0,
                "y": 4544.0
            }
        },
        {
            "cellIndex": 58,
            "meshAssetID": "{A9A3BC4D-F9EB-5CC5-BF7E-5D794A66F823}",
            "worldPosition": {
                "x": 5440.0,
                "y": 4544.0
            }
        },
        {
            "cellIndex": 59,
            "meshAssetID": "{43E940C2-DF17-5E26-8C5E-FEED483DBB6E}",
            "worldPosition": {
                "x": 5568.0,
                "y": 4544.0
            }
        },
        {
            "cellIndex": 60,
            "meshAssetID": "{880083FD-4BC8-5B21-8426-B24E54098B9B}",
            "worldPosition": {
                "x": 5696.0,
                "y": 4544.0
            }
        },
        {
            "cellIndex": 61,
            "meshAssetID": "{9D5A2880-2AC1-5275-B724-8F7E74A6AF4B}",
            "worldPosition": {
                "x": 5824.0,
                "y": 4544.0
            }
        },
        {
            "cellIndex": 62,
            "meshAssetID": "{9841A93C-C60D-5635-B2E1-AE60F4E00880}",
            "worldPosition": {
                "x": 5952.0,
                "y": 4544.0
            }
        },
        {
            "cellIndex": 63,
            "meshAssetID": "{686960E6-9178-5282-A1D1-BF22AF99E59F}",
            "worldPosition": {
                "x": 6080.0,
                "y": 4544.0
            }
        },
        {
            "cellIndex": 69,
            "meshAssetID": "{C33D323E-E494-5E40-97D8-C464EB4C63C3}",
            "worldPosition": {
                "x": 4800.0,
                "y": 4672.0
            }
        },
        {
            "cellIndex": 75,
            "meshAssetID": "{0501B680-EA2D-519F-801E-D1C65F591E65}",
            "worldPosition": {
                "x": 5568.0,
                "y": 4672.0
            }
        },
        {
            "cellIndex": 76,
            "meshAssetID": "{6DFCB1BE-24E0-5E92-8E97-0585A5F1E7A5}",
            "worldPosition": {
                "x": 5696.0,
                "y": 4672.0
            }
        },
        {
            "cellIndex": 77,
            "meshAssetID": "{75FCC62B-BFBA-5846-A0A1-43C508EB6E31}",
            "worldPosition": {
                "x": 5824.0,
                "y": 4672.0
            }
        },
        {
            "cellIndex": 78,
            "meshAssetID": "{0818C468-CE9A-5182-99A0-28F79AED798E}",
            "worldPosition": {
                "x": 5952.0,
                "y": 4672.0
            }
        },
        {
            "cellIndex": 79,
            "meshAssetID": "{30D63C50-FAD3-5D0C-9432-3D62AEDBB33A}",
            "worldPosition": {
                "x": 6080.0,
                "y": 4672.0
            }
        },
        {
            "cellIndex": 90,
            "meshAssetID": "{823A27AE-58C1-5334-AE56-50AA0B00AA0B}",
            "worldPosition": {
                "x": 5440.0,
                "y": 4800.0
            }
        },
        {
            "cellIndex": 91,
            "meshAssetID": "{0379A4FB-6C29-52D8-A8AC-36F294E487F1}",
            "worldPosition": {
                "x": 5568.0,
                "y": 4800.0
            }
        },
        {
            "cellIndex": 92,
            "meshAssetID": "{471182F1-58A6-5765-B6B2-D89B9BAEE605}",
            "worldPosition": {
                "x": 5696.0,
                "y": 4800.0
            }
        },
        {
            "cellIndex": 93,
            "meshAssetID": "{79B4C30D-FDD0-5596-AA4E-E80E722BE130}",
            "worldPosition": {
                "x": 5824.0,
                "y": 4800.0
            }
        },
        {
            "cellIndex": 95,
            "meshAssetID": "{D7F36663-BADC-53A5-AD1A-19A88C2ECCF3}",
            "worldPosition": {
                "x": 6080.0,
                "y": 4800.0
            }
        },
        {
            "cellIndex": 107,
            "meshAssetID": "{170BED28-5C89-50AE-872C-2C1DE54073AE}",
            "worldPosition": {
                "x": 5568.0,
                "y": 4928.0
            }
        },
        {
            "cellIndex": 108,
            "meshAssetID": "{89626BEB-3FE6-5776-B965-53636B497767}",
            "worldPosition": {
                "x": 5696.0,
                "y": 4928.0
            }
        },
        {
            "cellIndex": 109,
            "meshAssetID": "{D0DDFB6F-520B-56FA-8DBC-972F3C1D7F1B}",
            "worldPosition": {
                "x": 5824.0,
                "y": 4928.0
            }
        },
        {
            "cellIndex": 110,
            "meshAssetID": "{AD6E2771-6645-5CC8-88C4-05CE884F88E9}",
            "worldPosition": {
                "x": 5952.0,
                "y": 4928.0
            }
        },
        {
            "cellIndex": 111,
            "meshAssetID": "{413F5527-B738-5173-8A1B-4AB9D58C62F5}",
            "worldPosition": {
                "x": 6080.0,
                "y": 4928.0
            }
        },
        {
            "cellIndex": 124,
            "meshAssetID": "{F768314D-813F-5AD4-B74D-0EDF37320D62}",
            "worldPosition": {
                "x": 5696.0,
                "y": 5056.0
            }
        },
        {
            "cellIndex": 125,
            "meshAssetID": "{EDE7044F-0BC5-5DD2-B999-0D924CEC2381}",
            "worldPosition": {
                "x": 5824.0,
                "y": 5056.0
            }
        },
        {
            "cellIndex": 126,
            "meshAssetID": "{1AACC03B-9D04-5453-8767-DBEB618751BB}",
            "worldPosition": {
                "x": 5952.0,
                "y": 5056.0
            }
        },
        {
            "cellIndex": 127,
            "meshAssetID": "{34E7E3E1-4D72-5511-B4FC-39C45CE55E24}",
            "worldPosition": {
                "x": 6080.0,
                "y": 5056.0
            }
        },
        {
            "cellIndex": 141,
            "meshAssetID": "{5E742A65-E1E8-5C94-A812-C14158125885}",
            "worldPosition": {
                "x": 5824.0,
                "y": 5184.0
            }
        },
        {
            "cellIndex": 142,
            "meshAssetID": "{13C86F85-948D-5D34-80F4-8E9A523A03D2}",
            "worldPosition": {
                "x": 5952.0,
                "y": 5184.0
            }
        },
        {
            "cellIndex": 143,
            "meshAssetID": "{E78591B2-265C-5C67-BCFD-E109D3200BF3}",
            "worldPosition": {
                "x": 6080.0,
                "y": 5184.0
            }
        },
        {
            "cellIndex": 157,
            "meshAssetID": "{EFFE143C-78EF-5074-932D-7A1A483A5619}",
            "worldPosition": {
                "x": 5824.0,
                "y": 5312.0
            }
        },
        {
            "cellIndex": 158,
            "meshAssetID": "{EAA98712-FE8D-5B9B-9722-44D01911D293}",
            "worldPosition": {
                "x": 5952.0,
                "y": 5312.0
            }
        },
        {
            "cellIndex": 159,
            "meshAssetID": "{E351950B-67B9-5B5C-807D-2D09A40F137D}",
            "worldPosition": {
                "x": 6080.0,
                "y": 5312.0
            }
        },
        {
            "cellIndex": 173,
            "meshAssetID": "{4E074CE4-CF12-5845-A145-77A37BB896A6}",
            "worldPosition": {
                "x": 5824.0,
                "y": 5440.0
            }
        },
        {
            "cellIndex": 174,
            "meshAssetID": "{6B124E79-8AF7-509F-A342-FCDF6F172D1E}",
            "worldPosition": {
                "x": 5952.0,
                "y": 5440.0
            }
        },
        {
            "cellIndex": 189,
            "meshAssetID": "{44F6AF8B-C4BC-550B-9274-25B816BF707D}",
            "worldPosition": {
                "x": 5824.0,
                "y": 5568.0
            }
        }
    ]
}