{
    "Capitals": [
        {
            "id": "9fdd1076-6417-f5de-1804-11553e39ae2a",
            "worldPosition": {
                "x": 11264.0,
                "y": 3072.0,
                "z": 80.244384765625
            },
            "rotation": {
                "x": 0.0,
                "y": 0.0,
                "z": 0.0,
                "w": 1.0
            },
            "footprint": {
                "type": "Circle",
                "id": "813d97fc-f059-e707-d1c7-1b6f5f5ebca8",
                "radius": 0.0
            },
            "sliceName": "slices/Test/Zones/51_TractRef",
            "sliceAssetId": "{571C05E9-1C84-5079-AE31-4913DEE77435}:2"
        }
    ]
}