{
    "Capitals": [
        {
            "id": "9385df6c-6283-a5b0-5daf-b225ed0d46f6",
            "worldPosition": {
                "x": 8271.76171875,
                "y": 1284.7088623046875,
                "z": 207.21707153320313
            },
            "rotation": {
                "x": 0.0,
                "y": 0.0,
                "z": 0.29237163066864016,
                "w": 0.9563047885894775
            },
            "footprint": {
                "type": "Circle",
                "id": "36560e94-f698-b62c-d98b-bd1abc5565d2",
                "radius": 1.0
            },
            "sliceName": "CoatGen\\fe8d41a8\\Den_Cave_Arena_B_Yeti_bb_9385df6c6283a5b05dafb225ed0d46f6",
            "sliceAssetId": "{20D99C45-B161-53A2-956C-07867CFB95B1}:d46f6",
            "params": {
                "HAS_VEG_COMPONENTS": "1"
            }
        }
    ]
}